CODE_OF_CONDUCT.md
CONTRIBUTING.md
LICENSE
MANIFEST.in
NOTICE
README.md
requirements.txt
setup.cfg
setup.py
docs/long_description.md
xfer/__init__.py
xfer/__version__.py
xfer/bnn_classifier.py
xfer/bnn_repurposer.py
xfer/constants.py
xfer/gp_repurposer.py
xfer/load_repurposer.py
xfer/lr_repurposer.py
xfer/meta_model_repurposer.py
xfer/neural_network_fine_tune_repurposer.py
xfer/neural_network_random_freeze_repurposer.py
xfer/neural_network_repurposer.py
xfer/repurposer.py
xfer/svm_repurposer.py
xfer/utils.py
xfer/contrib/__init__.py
xfer/contrib/xfer_leap/__init__.py
xfer/contrib/xfer_leap/config.py
xfer/contrib/xfer_leap/data.py
xfer/contrib/xfer_leap/leap.py
xfer/contrib/xfer_leap/leap_meta_repurposer.py
xfer/contrib/xfer_leap/meta_repurposer.py
xfer/contrib/xfer_leap/metalogger.py
xfer/contrib/xfer_leap/onmiglot.py
xfer/contrib/xfer_leap/synthetic_data.py
xfer/contrib/xfer_leap/updaters.py
xfer/contrib/xfer_leap/utils.py
xfer/contrib/xfer_leap/test/__init__.py
xfer/contrib/xfer_leap/test/mxnet_test.py
xfer/model_handler/__init__.py
xfer/model_handler/consts.py
xfer/model_handler/exceptions.py
xfer/model_handler/model_handler.py
xfer/prob/__init__.py
xfer/prob/obs.py
xfer/prob/prior.py
xfer/prob/prob_base.py
xfer/prob/utils.py
xfer/prob/var.py
xfer/prob/var_loss.py
xfer_ml.egg-info/PKG-INFO
xfer_ml.egg-info/SOURCES.txt
xfer_ml.egg-info/dependency_links.txt
xfer_ml.egg-info/requires.txt
xfer_ml.egg-info/top_level.txt